promptflow_clinical_rwd/__init__.py
promptflow_clinical_rwd/tools/__init__.py
promptflow_clinical_rwd/tools/clinical_note_summarization.py
promptflow_clinical_rwd/tools/structured_prediction.py
promptflow_clinical_rwd/tools/utils.py
promptflow_clinical_rwd/yamls/clinical_note_summarization.yaml
promptflow_clinical_rwd/yamls/structured_prediction.yaml
tests/__init__.py
tests/test_clinical_rwd.py
promptflow_clinical_rwd-0.0.9.dist-info/METADATA
promptflow_clinical_rwd-0.0.9.dist-info/WHEEL
promptflow_clinical_rwd-0.0.9.dist-info/entry_points.txt
promptflow_clinical_rwd-0.0.9.dist-info/top_level.txt
promptflow_clinical_rwd-0.0.9.dist-info/RECORD
