Metadata-Version: 2.1
Name: promptflow-clinical-rwd
Version: 0.0.9
Summary: This is my tools package
